odoo/addons/edi_xml_oca/README.rst
odoo/addons/edi_xml_oca/__init__.py
odoo/addons/edi_xml_oca/__manifest__.py
odoo/addons/edi_xml_oca/xmler.py
odoo/addons/edi_xml_oca/components/__init__.py
odoo/addons/edi_xml_oca/components/xml_handler.py
odoo/addons/edi_xml_oca/i18n/edi_xml.pot
odoo/addons/edi_xml_oca/i18n/edi_xml_oca.pot
odoo/addons/edi_xml_oca/i18n/it.po
odoo/addons/edi_xml_oca/readme/CONTRIBUTORS.rst
odoo/addons/edi_xml_oca/readme/DESCRIPTION.rst
odoo/addons/edi_xml_oca/static/description/icon.png
odoo/addons/edi_xml_oca/static/description/index.html
odoo/addons/edi_xml_oca/tests/__init__.py
odoo/addons/edi_xml_oca/tests/common.py
odoo/addons/edi_xml_oca/tests/test_xml.py
odoo/addons/edi_xml_oca/tests/fixtures/Test.xsd
odoo14_addon_edi_xml_oca-14.0.1.1.1.dist-info/METADATA
odoo14_addon_edi_xml_oca-14.0.1.1.1.dist-info/WHEEL
odoo14_addon_edi_xml_oca-14.0.1.1.1.dist-info/top_level.txt
odoo14_addon_edi_xml_oca-14.0.1.1.1.dist-info/RECORD
