Metadata-Version: 2.1
Name: odoo14-addon-edi_xml_oca
Version: 14.0.1.1.1
Summary: Base module for EDI exchange using XML files.
Home-page: https://github.com/OCA/edi
Author: ACSONE,Camptocamp,Odoo Community Association (OCA)
Author-email: support@odoo-community.org
License: LGPL-3
Classifier: Programming Language :: Python
Classifier: Framework :: Odoo
Classifier: Framework :: Odoo :: 14.0
Classifier: License :: OSI Approved :: GNU Lesser General Public License v3 (LGPLv3)
Classifier: Development Status :: 3 - Alpha
Requires-Python: >=3.6
Requires-Dist: odoo14-addon-component
Requires-Dist: odoo14-addon-edi-oca
Requires-Dist: odoo<14.1dev,>=14.0a
Requires-Dist: xmlschema
